LICENSE
README.md
pyproject.toml
setup.py
docs/requirements.txt
src/pythonwrench/__init__.py
src/pythonwrench/__main__.py
src/pythonwrench/_core.py
src/pythonwrench/abc.py
src/pythonwrench/argparse.py
src/pythonwrench/cast.py
src/pythonwrench/checksum.py
src/pythonwrench/concurrent.py
src/pythonwrench/csv.py
src/pythonwrench/dataclasses.py
src/pythonwrench/datetime.py
src/pythonwrench/difflib.py
src/pythonwrench/disk_cache.py
src/pythonwrench/entries.py
src/pythonwrench/enum.py
src/pythonwrench/functools.py
src/pythonwrench/hashlib.py
src/pythonwrench/importlib.py
src/pythonwrench/inspect.py
src/pythonwrench/json.py
src/pythonwrench/jsonl.py
src/pythonwrench/logging.py
src/pythonwrench/math.py
src/pythonwrench/os.py
src/pythonwrench/pickle.py
src/pythonwrench/random.py
src/pythonwrench/re.py
src/pythonwrench/semver.py
src/pythonwrench/warnings.py
src/pythonwrench.egg-info/PKG-INFO
src/pythonwrench.egg-info/SOURCES.txt
src/pythonwrench.egg-info/dependency_links.txt
src/pythonwrench.egg-info/entry_points.txt
src/pythonwrench.egg-info/requires.txt
src/pythonwrench.egg-info/top_level.txt
src/pythonwrench/collections/__init__.py
src/pythonwrench/collections/collections.py
src/pythonwrench/collections/prop.py
src/pythonwrench/collections/reducers.py
src/pythonwrench/typing/__init__.py
src/pythonwrench/typing/checks.py
src/pythonwrench/typing/classes.py
tests/test_abc.py
tests/test_argparse.py
tests/test_cast.py
tests/test_checksum.py
tests/test_collections.py
tests/test_csv.py
tests/test_dataclasses.py
tests/test_difflib.py
tests/test_disk_cache.py
tests/test_entries.py
tests/test_enum.py
tests/test_functools.py
tests/test_hashlib.py
tests/test_importlib.py
tests/test_inspect.py
tests/test_json.py
tests/test_jsonl.py
tests/test_logging.py
tests/test_math.py
tests/test_os.py
tests/test_random.py
tests/test_readme.py
tests/test_semver.py
tests/test_typing.py