Metadata-Version: 2.1
Name: pythonwrench
Version: 0.4.6
Summary: Python library with tools for typing, manipulating collections, and more!
Author-email: "Étienne Labbé (Labbeti)" <labbeti.pub@gmail.com>
Maintainer-email: "Étienne Labbé (Labbeti)" <labbeti.pub@gmail.com>
License: MIT License
Project-URL: Homepage, https://pypi.org/project/pythonwrench/
Project-URL: Documentation, https://pythonwrench.readthedocs.io/
Project-URL: Repository, https://github.com/Labbeti/pythonwrench.git
Project-URL: Changelog, https://github.com/Labbeti/pythonwrench/blob/main/CHANGELOG.md
Project-URL: Tracker, https://github.com/Labbeti/pythonwrench/issues
Keywords: python,tools,utilities
Classifier: Intended Audience :: Developers
Classifier: Intended Audience :: Science/Research
Classifier: Programming Language :: Python :: 3
Classifier: Programming Language :: Python :: 3.8
Classifier: Programming Language :: Python :: 3.9
Classifier: Programming Language :: Python :: 3.10
Classifier: Programming Language :: Python :: 3.11
Classifier: Programming Language :: Python :: 3.12
Classifier: Programming Language :: Python :: 3.13
Classifier: Programming Language :: Python :: 3.14
Classifier: Topic :: Scientific/Engineering
Classifier: Operating System :: OS Independent
Classifier: Operating System :: MacOS :: MacOS X
Classifier: Operating System :: Microsoft :: Windows
Classifier: Operating System :: POSIX
Requires-Python: <3.15,>=3.8
License-File: LICENSE
Requires-Dist: typing-extensions>=4.10.0
Provides-Extra: dev
